sample/__init__.py
sample/simple.py
schubert/__init__.py
schubert/simple.py
schubert/febraban/__init__.py
schubert/febraban/barcode.py
schubert/itau/__init__.py
schubert/itau/dac.py
tests/__init__.py
tests/test_simple.py
schubert-0.0.6.dist-info/LICENSE.txt
schubert-0.0.6.dist-info/METADATA
schubert-0.0.6.dist-info/WHEEL
schubert-0.0.6.dist-info/top_level.txt
schubert-0.0.6.dist-info/RECORD
